args_to_db/__init__.py
args_to_db/commands/__init__.py
args_to_db/commands/args.py
args_to_db/commands/combine.py
args_to_db/commands/command.py
args_to_db/commands/command_builder.py
args_to_db/commands/commandlist.py
args_to_db/control/__init__.py
args_to_db/control/command_failed_exception.py
args_to_db/control/result_thread.py
args_to_db/control/run.py
args_to_db/control/run_result.py
args_to_db/control/state.py
args_to_db/runtime/__init__.py
args_to_db/runtime/result.py
args_to_db/utility/__init__.py
args_to_db/utility/logger.py
args_to_db-0.1.7.dist-info/LICENSE
args_to_db-0.1.7.dist-info/METADATA
args_to_db-0.1.7.dist-info/WHEEL
args_to_db-0.1.7.dist-info/top_level.txt
args_to_db-0.1.7.dist-info/RECORD
