Metadata-Version: 2.1
Name: args-to-db
Version: 0.1.7
Summary: Runs python script in argument combinations and produces dataset of all results.
Home-page: https://github.com/schnellerhase/args_to_db
Author: schnellerhase
License: GPLv3
Keywords: arguments,pandas,automatisation
Platform: UNKNOWN
Classifier: Development Status :: 2 - Pre-Alpha
Classifier: Intended Audience :: Developers
Classifier: Intended Audience :: Information Technology
Classifier: Intended Audience :: Science/Research
Classifier: License :: OSI Approved :: GNU General Public License v3 (GPLv3)
Classifier: Natural Language :: English
Classifier: Operating System :: OS Independent
Classifier: Programming Language :: Python :: 3.0
Classifier: Programming Language :: Python :: 3.1
Classifier: Programming Language :: Python :: 3.10
Classifier: Programming Language :: Python :: 3.2
Classifier: Programming Language :: Python :: 3.3
Classifier: Programming Language :: Python :: 3.4
Classifier: Programming Language :: Python :: 3.5
Classifier: Programming Language :: Python :: 3.6
Classifier: Programming Language :: Python :: 3.7
Classifier: Programming Language :: Python :: 3.8
Classifier: Programming Language :: Python :: 3.9
Classifier: Programming Language :: Python :: 3
Classifier: Programming Language :: Python
Classifier: Topic :: Scientific/Engineering
Classifier: Topic :: System :: Benchmark
Classifier: Topic :: System :: Distributed Computing
Classifier: Topic :: Utilities
License-File: LICENSE
Requires-Dist: pandas
Requires-Dist: cursor
Provides-Extra: dev
Requires-Dist: bandit ; extra == 'dev'
Requires-Dist: mypy ; extra == 'dev'
Requires-Dist: numpy ; extra == 'dev'
Requires-Dist: parameterized ; extra == 'dev'
Requires-Dist: prospector ; extra == 'dev'
Requires-Dist: pylint ; extra == 'dev'
Requires-Dist: pyroma ; extra == 'dev'
Requires-Dist: pytest ; extra == 'dev'
Requires-Dist: scipy ; extra == 'dev'
Requires-Dist: setuptools ; extra == 'dev'
